finitedepth_ifd/__init__.py
finitedepth_ifd/__init__.pyi
finitedepth_ifd/py.typed
dipcoatimage_finitedepth_ifd-0.3.0.dist-info/LICENSE
dipcoatimage_finitedepth_ifd-0.3.0.dist-info/METADATA
dipcoatimage_finitedepth_ifd-0.3.0.dist-info/WHEEL
dipcoatimage_finitedepth_ifd-0.3.0.dist-info/entry_points.txt
dipcoatimage_finitedepth_ifd-0.3.0.dist-info/top_level.txt
dipcoatimage_finitedepth_ifd-0.3.0.dist-info/RECORD
