Metadata-Version: 2.1
Name: dipcoatimage-finitedepth-ifd
Version: 0.3.0
Summary: Measure finite depth dip coating roughness with integral Fréchet distance.
Author-email: Jisoo Song <jeesoo9595@snu.ac.kr>
License: BSD 2-Clause License
Project-URL: homepage, https://github.com/dipcoat-image/finitedepth-ifd
Project-URL: source, https://github.com/dipcoat-image/finitedepth-ifd
Project-URL: documentation, https://dipcoatimage-finitedepth-ifd.readthedocs.io
Classifier: Development Status :: 4 - Beta
Classifier: Intended Audience :: Science/Research
Classifier: License :: OSI Approved :: BSD License
Classifier: Programming Language :: Python
Classifier: Programming Language :: Python :: 3
Classifier: Programming Language :: Python :: 3.10
Classifier: Programming Language :: Python :: 3.11
Classifier: Programming Language :: Python :: 3.12
Classifier: Programming Language :: Python :: 3 :: Only
Classifier: Topic :: Scientific/Engineering
Classifier: Topic :: Scientific/Engineering :: Physics
Classifier: Typing :: Typed
Classifier: Operating System :: OS Independent
Requires-Python: >=3.10
License-File: LICENSE
Requires-Dist: dipcoatimage-finitedepth >=2.0.5
Requires-Dist: curvesimilarities >=0.2.0
Requires-Dist: numpy <2
Provides-Extra: dev
Requires-Dist: flake8 ; extra == 'dev'
Requires-Dist: flake8-pyi ; extra == 'dev'
Requires-Dist: flake8-docstrings ; extra == 'dev'
Requires-Dist: black ; extra == 'dev'
Requires-Dist: isort ; extra == 'dev'
Requires-Dist: docformatter ; extra == 'dev'
Requires-Dist: doc8 ; extra == 'dev'
Requires-Dist: mypy ; extra == 'dev'
Requires-Dist: dipcoatimage-finitedepth-ifd[doc,test] ; extra == 'dev'
Provides-Extra: doc
Requires-Dist: sphinx ; extra == 'doc'
Requires-Dist: numpydoc ; extra == 'doc'
Requires-Dist: pydata-sphinx-theme ; extra == 'doc'
Requires-Dist: matplotlib ; extra == 'doc'
Provides-Extra: test
Requires-Dist: pytest ; extra == 'test'
